[
  {
    "source": "Pierre-Séverin Luino",
    "target": "Jacques Pills",
    "targetId": "1142"
  },
  {
    "source": "Pierre-Séverin Luino",
    "target": "Tony Rovira",
    "targetId": "1143"
  },
  {
    "source": "Pierre-Séverin Luino",
    "target": "Armand Molinetti",
    "targetId": "1144"
  },
  {
    "source": "Pierre-Séverin Luino",
    "target": "Joseph Reinhardt",
    "targetId": "1145"
  },
  {
    "source": "Pierre-Séverin Luino",
    "target": "Paul Collot",
    "targetId": "1146"
  },
  {
    "source": "Pierre-Séverin Luino",
    "target": "Charles Lisée",
    "targetId": "1147"
  },
  {
    "source": "Pierre-Séverin Luino",
    "target": "Max Blanc",
    "targetId": "1148"
  },
  {
    "source": "Pierre-Séverin Luino",
    "target": "Alix Combelle",
    "targetId": "1149"
  },
  {
    "source": "Pierre-Séverin Luino",
    "target": "Charles Hary",
    "targetId": "1150"
  },
  {
    "source": "Pierre-Séverin Luino",
    "target": "Jean Luino",
    "targetId": "1151"
  },
  {
    "source": "Pierre-Séverin Luino",
    "target": "Maurice Gladieu",
    "targetId": "1152"
  },
  {
    "source": "Pierre-Séverin Luino",
    "target": "Aimé Barelli",
    "targetId": "1153"
  },
  {
    "source": "Pierre-Séverin Luino",
    "target": "Christian Bellest",
    "targetId": "1154"
  }
]