{
  "source": "Beverly Dahike-Smith",
  "trackCount": 1,
  "tracks": [
    {
      "_id": "941",
      "names": [
        "Pep Talk"
      ],
      "releases": [
        {
          "_id": "283",
          "names": [
            "If It Don't Kill You, It Just Makes You Stronger"
          ]
        }
      ]
    }
  ],
  "targets": [
    {
      "name": "Bruce Willis",
      "targetId": "1382",
      "trackCount": 1
    },
    {
      "name": "Greg Smith",
      "targetId": "1383",
      "trackCount": 1
    },
    {
      "name": "Robben Ford",
      "targetId": "1385",
      "trackCount": 1
    },
    {
      "name": "Garrett Adkins",
      "targetId": "1386",
      "trackCount": 1
    },
    {
      "name": "John Thomas",
      "targetId": "1387",
      "trackCount": 1
    },
    {
      "name": "Roscoe Beck",
      "targetId": "1388",
      "trackCount": 1
    },
    {
      "name": "Tom Brechtlein",
      "targetId": "1389",
      "trackCount": 1
    },
    {
      "name": "David Grissom",
      "targetId": "1390",
      "trackCount": 1
    },
    {
      "name": "William Smith",
      "targetId": "1391",
      "trackCount": 1
    },
    {
      "name": "Joe Sublett",
      "targetId": "1392",
      "trackCount": 1
    },
    {
      "name": "Darrel Leonard",
      "targetId": "1393",
      "trackCount": 1
    }
  ]
}