{
  "source": "Phil Rizzuto",
  "targets": [
    {
      "name": "Roy Bittan",
      "targetId": "463"
    },
    {
      "name": "Max Weinberg",
      "targetId": "468"
    },
    {
      "name": "Edgar Winter",
      "targetId": "1423"
    },
    {
      "name": "Meat Loaf",
      "targetId": "1803"
    },
    {
      "name": "Kasim Sulton",
      "targetId": "1814"
    },
    {
      "name": "Ellen Foley",
      "targetId": "1815"
    },
    {
      "name": "Rory Dodd",
      "targetId": "1816"
    },
    {
      "name": "Todd Rundgren",
      "targetId": "1817"
    },
    {
      "name": "Marvin Lee",
      "targetId": "1819"
    }
  ]
}