{
  "source": "Ednah Holt",
  "trackCount": 1,
  "tracks": [
    {
      "_id": "30",
      "names": [
        "Take Me To The River"
      ],
      "releases": [
        {
          "_id": "25",
          "names": [
            "Stop Making Sense"
          ]
        }
      ]
    }
  ],
  "targets": [
    {
      "name": "Jerry Harrison",
      "targetId": "192",
      "trackCount": 1
    },
    {
      "name": "David Byrne",
      "targetId": "193",
      "trackCount": 1
    },
    {
      "name": "Tina Weymouth",
      "targetId": "194",
      "trackCount": 1
    },
    {
      "name": "Chris Frantz",
      "targetId": "195",
      "trackCount": 1
    },
    {
      "name": "Lynn Mabry",
      "targetId": "197",
      "trackCount": 1
    },
    {
      "name": "Alex Weir",
      "targetId": "198",
      "trackCount": 1
    },
    {
      "name": "Bernie Worrell",
      "targetId": "199",
      "trackCount": 1
    },
    {
      "name": "Steve Scales",
      "targetId": "200",
      "trackCount": 1
    }
  ]
}