[
  {
    "source": "Kardinal Offishall",
    "target": "Jim Creeggan",
    "targetId": "1137"
  },
  {
    "source": "Kardinal Offishall",
    "target": "Jully Black",
    "targetId": "2185"
  },
  {
    "source": "Kardinal Offishall",
    "target": "Korry Deez",
    "targetId": "2187"
  },
  {
    "source": "Kardinal Offishall",
    "target": "DJ Kardi Rock",
    "targetId": "2188"
  },
  {
    "source": "Kardinal Offishall",
    "target": "Allistair",
    "targetId": "2189"
  },
  {
    "source": "Kardinal Offishall",
    "target": "Black Cat",
    "targetId": "2190"
  },
  {
    "source": "Kardinal Offishall",
    "target": "Wio-K",
    "targetId": "2191"
  },
  {
    "source": "Kardinal Offishall",
    "target": "Tom Cochrane",
    "targetId": "2498"
  },
  {
    "source": "Kardinal Offishall",
    "target": "Kathleen Edwards",
    "targetId": "3661"
  },
  {
    "source": "Kardinal Offishall",
    "target": "Nelly Furtado",
    "targetId": "6013"
  },
  {
    "source": "Kardinal Offishall",
    "target": "Avril Lavigne",
    "targetId": "6292"
  },
  {
    "source": "Kardinal Offishall",
    "target": "Deryck Whibley",
    "targetId": "6297"
  },
  {
    "source": "Kardinal Offishall",
    "target": "Jacob Hoggard",
    "targetId": "6893"
  },
  {
    "source": "Kardinal Offishall",
    "target": "Esthero",
    "targetId": "7030"
  },
  {
    "source": "Kardinal Offishall",
    "target": "Emily Haines",
    "targetId": "7316"
  },
  {
    "source": "Kardinal Offishall",
    "target": "Kevin Drew",
    "targetId": "8181"
  },
  {
    "source": "Kardinal Offishall",
    "target": "Drake",
    "targetId": "8201"
  },
  {
    "source": "Kardinal Offishall",
    "target": "Justin Bieber",
    "targetId": "8443"
  },
  {
    "source": "Kardinal Offishall",
    "target": "Pierre Bouvier",
    "targetId": "8547"
  },
  {
    "source": "Kardinal Offishall",
    "target": "Brendan Canning",
    "targetId": "8548"
  },
  {
    "source": "Kardinal Offishall",
    "target": "K'naan",
    "targetId": "8549"
  },
  {
    "source": "Kardinal Offishall",
    "target": "Sam Roberts",
    "targetId": "8550"
  },
  {
    "source": "Kardinal Offishall",
    "target": "Tyler Connolly",
    "targetId": "8551"
  },
  {
    "source": "Kardinal Offishall",
    "target": "Josh Ramsay",
    "targetId": "8552"
  },
  {
    "source": "Kardinal Offishall",
    "target": "Jay Malinowski",
    "targetId": "8553"
  },
  {
    "source": "Kardinal Offishall",
    "target": "Chin Injeti",
    "targetId": "8554"
  },
  {
    "source": "Kardinal Offishall",
    "target": "Red1",
    "targetId": "8555"
  },
  {
    "source": "Kardinal Offishall",
    "target": "Lights",
    "targetId": "8556"
  },
  {
    "source": "Kardinal Offishall",
    "target": "Serena Ryder",
    "targetId": "8557"
  },
  {
    "source": "Kardinal Offishall",
    "target": "James Shaw",
    "targetId": "8558"
  },
  {
    "source": "Kardinal Offishall",
    "target": "Hawksley Workman",
    "targetId": "8559"
  },
  {
    "source": "Kardinal Offishall",
    "target": "Ima",
    "targetId": "8560"
  },
  {
    "source": "Kardinal Offishall",
    "target": "Elisapie Isaac",
    "targetId": "8561"
  },
  {
    "source": "Kardinal Offishall",
    "target": "Pierre Lapointe",
    "targetId": "8562"
  },
  {
    "source": "Kardinal Offishall",
    "target": "Corb Lund",
    "targetId": "8563"
  },
  {
    "source": "Kardinal Offishall",
    "target": "Fefe Dobson",
    "targetId": "8564"
  },
  {
    "source": "Kardinal Offishall",
    "target": "Kevin Parent",
    "targetId": "8565"
  },
  {
    "source": "Kardinal Offishall",
    "target": "Lamar Ashe",
    "targetId": "8566"
  },
  {
    "source": "Kardinal Offishall",
    "target": "Colin James",
    "targetId": "8567"
  },
  {
    "source": "Kardinal Offishall",
    "target": "Nikki Yanofsky",
    "targetId": "8568"
  },
  {
    "source": "Kardinal Offishall",
    "target": "Suzie McNeil",
    "targetId": "8569"
  },
  {
    "source": "Kardinal Offishall",
    "target": "Stephan Moccio",
    "targetId": "8570"
  },
  {
    "source": "Kardinal Offishall",
    "target": "Aoin Clarke",
    "targetId": "8571"
  },
  {
    "source": "Kardinal Offishall",
    "target": "Jim Cuddy",
    "targetId": "8572"
  },
  {
    "source": "Kardinal Offishall",
    "target": "Shiloh",
    "targetId": "8573"
  },
  {
    "source": "Kardinal Offishall",
    "target": "Stacey McKitrick",
    "targetId": "8574"
  },
  {
    "source": "Kardinal Offishall",
    "target": "Jessie Farrell",
    "targetId": "8575"
  },
  {
    "source": "Kardinal Offishall",
    "target": "Colin MacDonald",
    "targetId": "8576"
  },
  {
    "source": "Kardinal Offishall",
    "target": "Justin Nozuka",
    "targetId": "8577"
  },
  {
    "source": "Kardinal Offishall",
    "target": "Hayley Sales",
    "targetId": "8578"
  },
  {
    "source": "Kardinal Offishall",
    "target": "Matt Mays",
    "targetId": "8579"
  },
  {
    "source": "Kardinal Offishall",
    "target": "Dallas Green",
    "targetId": "8580"
  },
  {
    "source": "Kardinal Offishall",
    "target": "Pat Kordyback",
    "targetId": "8581"
  },
  {
    "source": "Kardinal Offishall",
    "target": "Dave Faber",
    "targetId": "8582"
  },
  {
    "source": "Kardinal Offishall",
    "target": "Brandon Lehti",
    "targetId": "8583"
  },
  {
    "source": "Kardinal Offishall",
    "target": "Torquil Campbell",
    "targetId": "8584"
  },
  {
    "source": "Kardinal Offishall",
    "target": "Remigio Pereira",
    "targetId": "8585"
  },
  {
    "source": "Kardinal Offishall",
    "target": "Victor Micallef",
    "targetId": "8586"
  },
  {
    "source": "Kardinal Offishall",
    "target": "Fraser Walters",
    "targetId": "8587"
  },
  {
    "source": "Kardinal Offishall",
    "target": "Clifton Murray",
    "targetId": "8588"
  },
  {
    "source": "Kardinal Offishall",
    "target": "Max Kerman",
    "targetId": "8589"
  },
  {
    "source": "Kardinal Offishall",
    "target": "Mike DeAngelis",
    "targetId": "8590"
  },
  {
    "source": "Kardinal Offishall",
    "target": "Dan Griffin",
    "targetId": "8591"
  },
  {
    "source": "Kardinal Offishall",
    "target": "Nick Dika",
    "targetId": "8592"
  },
  {
    "source": "Kardinal Offishall",
    "target": "Tim Oxford",
    "targetId": "8593"
  }
]