{
  "source": "Michael Thompson",
  "trackCount": 8,
  "targets": [
    {
      "name": "Ray Charles",
      "targetId": "50",
      "trackCount": 1
    },
    {
      "name": "Phil Collins",
      "targetId": "97",
      "trackCount": 1
    },
    {
      "name": "Chuck Findley",
      "targetId": "397",
      "trackCount": 1
    },
    {
      "name": "Paulinho Da Costa",
      "targetId": "411",
      "trackCount": 2
    },
    {
      "name": "Jack Nimitz",
      "targetId": "436",
      "trackCount": 1
    },
    {
      "name": "Craig Krampf",
      "targetId": "647",
      "trackCount": 1
    },
    {
      "name": "Greg Phillinganes",
      "targetId": "649",
      "trackCount": 3
    },
    {
      "name": "John \"J. R.\" Robinson",
      "targetId": "653",
      "trackCount": 3
    },
    {
      "name": "Elton John",
      "targetId": "805",
      "trackCount": 1
    },
    {
      "name": "Dan Higgins",
      "targetId": "1080",
      "trackCount": 1
    },
    {
      "name": "Herbie Hancock",
      "targetId": "1264",
      "trackCount": 1
    },
    {
      "name": "Jerry Hey",
      "targetId": "1322",
      "trackCount": 1
    },
    {
      "name": "Tom Fowler",
      "targetId": "1325",
      "trackCount": 1
    },
    {
      "name": "Gary Grant",
      "targetId": "1394",
      "trackCount": 1
    },
    {
      "name": "Bill Reichenbach",
      "targetId": "1395",
      "trackCount": 1
    },
    {
      "name": "Julia Waters",
      "targetId": "1401",
      "trackCount": 1
    },
    {
      "name": "Maxine Waters",
      "targetId": "1402",
      "trackCount": 1
    },
    {
      "name": "Gloria Estefan",
      "targetId": "1768",
      "trackCount": 1
    },
    {
      "name": "Luis Miguel",
      "targetId": "1774",
      "trackCount": 1
    },
    {
      "name": "Barry White",
      "targetId": "2078",
      "trackCount": 1
    },
    {
      "name": "Siedah Garrett",
      "targetId": "2081",
      "trackCount": 1
    },
    {
      "name": "Alan Pasqua",
      "targetId": "2263",
      "trackCount": 1
    },
    {
      "name": "John Acosta",
      "targetId": "2264",
      "trackCount": 1
    },
    {
      "name": "Rudolph Stein",
      "targetId": "2265",
      "trackCount": 1
    },
    {
      "name": "Steve Richards",
      "targetId": "2266",
      "trackCount": 1
    },
    {
      "name": "Yao Zhao",
      "targetId": "2267",
      "trackCount": 1
    },
    {
      "name": "Carolyn Riley",
      "targetId": "2268",
      "trackCount": 1
    },
    {
      "name": "Ed Persi",
      "targetId": "2269",
      "trackCount": 1
    },
    {
      "name": "Maria Newman",
      "targetId": "2270",
      "trackCount": 1
    },
    {
      "name": "Sam Formicola",
      "targetId": "2271",
      "trackCount": 1
    },
    {
      "name": "Alan Ellsworth",
      "targetId": "2272",
      "trackCount": 1
    },
    {
      "name": "Alicia Engley",
      "targetId": "2273",
      "trackCount": 1
    },
    {
      "name": "Amy Wickman-Guerra",
      "targetId": "2274",
      "trackCount": 1
    },
    {
      "name": "Dennis Molchan",
      "targetId": "2275",
      "trackCount": 1
    },
    {
      "name": "Edmund Stein",
      "targetId": "2276",
      "trackCount": 1
    },
    {
      "name": "Gerry Hilera",
      "targetId": "2277",
      "trackCount": 1
    },
    {
      "name": "Igor Pandurski",
      "targetId": "2278",
      "trackCount": 1
    },
    {
      "name": "Kathleen Robertson",
      "targetId": "2279",
      "trackCount": 1
    },
    {
      "name": "Nick Grant",
      "targetId": "2280",
      "trackCount": 1
    },
    {
      "name": "Paul Manaster",
      "targetId": "2281",
      "trackCount": 1
    },
    {
      "name": "Reginald Clews",
      "targetId": "2282",
      "trackCount": 1
    },
    {
      "name": "Sai Ly Acosta",
      "targetId": "2283",
      "trackCount": 1
    },
    {
      "name": "Todor Pelev",
      "targetId": "2284",
      "trackCount": 1
    },
    {
      "name": "Xiao Niu He",
      "targetId": "2285",
      "trackCount": 1
    },
    {
      "name": "Zheng Wang",
      "targetId": "2286",
      "trackCount": 1
    },
    {
      "name": "Richard Todd",
      "targetId": "2307",
      "trackCount": 1
    },
    {
      "name": "Neil Stubenhaus",
      "targetId": "2440",
      "trackCount": 1
    },
    {
      "name": "John Van Tongeren",
      "targetId": "2588",
      "trackCount": 1
    },
    {
      "name": "Maurice White",
      "targetId": "2787",
      "trackCount": 1
    },
    {
      "name": "Melvin \"Wah Wah\" Watson",
      "targetId": "3402",
      "trackCount": 1
    },
    {
      "name": "George Bohanon",
      "targetId": "3415",
      "trackCount": 1
    },
    {
      "name": "Cher",
      "targetId": "3456",
      "trackCount": 1
    },
    {
      "name": "Debra Dobkin",
      "targetId": "3483",
      "trackCount": 1
    },
    {
      "name": "Jimmy Haslip",
      "targetId": "3484",
      "trackCount": 1
    },
    {
      "name": "Mark Morgan",
      "targetId": "3485",
      "trackCount": 1
    },
    {
      "name": "Charles Loper",
      "targetId": "4222",
      "trackCount": 1
    },
    {
      "name": "Reggie Young",
      "targetId": "4223",
      "trackCount": 1
    },
    {
      "name": "Pete Christlieb",
      "targetId": "4224",
      "trackCount": 1
    },
    {
      "name": "Fred Jackson",
      "targetId": "4225",
      "trackCount": 1
    },
    {
      "name": "Jeff Clayton",
      "targetId": "4226",
      "trackCount": 1
    },
    {
      "name": "Patti Austin",
      "targetId": "4229",
      "trackCount": 1
    },
    {
      "name": "Joshua Redman",
      "targetId": "4232",
      "trackCount": 1
    },
    {
      "name": "Mervyn Warren",
      "targetId": "4247",
      "trackCount": 2
    },
    {
      "name": "Will Wheaton",
      "targetId": "4251",
      "trackCount": 1
    },
    {
      "name": "Gregory Williams",
      "targetId": "4273",
      "trackCount": 1
    },
    {
      "name": "Brad Warnaar",
      "targetId": "4274",
      "trackCount": 1
    },
    {
      "name": "Bob Watt",
      "targetId": "4275",
      "trackCount": 1
    },
    {
      "name": "Tommy Johnson",
      "targetId": "4276",
      "trackCount": 1
    },
    {
      "name": "Edwin Bonilla",
      "targetId": "4277",
      "trackCount": 1
    },
    {
      "name": "Warren Wiebe",
      "targetId": "4278",
      "trackCount": 1
    },
    {
      "name": "Toots Thielemans",
      "targetId": "4291",
      "trackCount": 1
    },
    {
      "name": "Martin Tillman",
      "targetId": "6107",
      "trackCount": 2
    },
    {
      "name": "Billy Sherwood",
      "targetId": "6279",
      "trackCount": 1
    },
    {
      "name": "Michael Sherwood",
      "targetId": "6280",
      "trackCount": 1
    },
    {
      "name": "Larry Antonino",
      "targetId": "7883",
      "trackCount": 3
    },
    {
      "name": "Mark Williams",
      "targetId": "7884",
      "trackCount": 3
    },
    {
      "name": "Guy Allison",
      "targetId": "7885",
      "trackCount": 2
    },
    {
      "name": "Russell Hitchcock",
      "targetId": "7886",
      "trackCount": 3
    },
    {
      "name": "Graham Russell",
      "targetId": "7887",
      "trackCount": 2
    },
    {
      "name": "Lili Haydn",
      "targetId": "7890",
      "trackCount": 1
    },
    {
      "name": "C.C. White",
      "targetId": "7891",
      "trackCount": 1
    }
  ]
}