[
  {
    "source": "Rutger Gunnarsson",
    "target": "Agnetha Fältskog",
    "targetId": "2698"
  },
  {
    "source": "Rutger Gunnarsson",
    "target": "Benny Andersson",
    "targetId": "2896"
  },
  {
    "source": "Rutger Gunnarsson",
    "target": "Anni-Frid Lyngstad",
    "targetId": "2897"
  },
  {
    "source": "Rutger Gunnarsson",
    "target": "Björn Ulvaeus",
    "targetId": "2898"
  },
  {
    "source": "Rutger Gunnarsson",
    "target": "Ola Brunkert",
    "targetId": "2900"
  },
  {
    "source": "Rutger Gunnarsson",
    "target": "Roger Palm",
    "targetId": "2901"
  },
  {
    "source": "Rutger Gunnarsson",
    "target": "Janne Schaffer",
    "targetId": "2902"
  },
  {
    "source": "Rutger Gunnarsson",
    "target": "Lasse Wellander",
    "targetId": "2903"
  },
  {
    "source": "Rutger Gunnarsson",
    "target": "Lars O. Carlsson",
    "targetId": "2905"
  }
]