[
  {
    "source": "Björk",
    "target": "Tricky",
    "targetId": "1714"
  },
  {
    "source": "Björk",
    "target": "Robert Wyatt",
    "targetId": "1953"
  },
  {
    "source": "Björk",
    "target": "Tagaq",
    "targetId": "3034"
  },
  {
    "source": "Björk",
    "target": "Mike Patton",
    "targetId": "3213"
  },
  {
    "source": "Björk",
    "target": "Siggi Baldursson",
    "targetId": "4548"
  },
  {
    "source": "Björk",
    "target": "Peter van Hooke",
    "targetId": "6467"
  },
  {
    "source": "Björk",
    "target": "Rahzel",
    "targetId": "6833"
  },
  {
    "source": "Björk",
    "target": "Einar Örn",
    "targetId": "7604"
  },
  {
    "source": "Björk",
    "target": "Bragi Ólafsson",
    "targetId": "7613"
  },
  {
    "source": "Björk",
    "target": "Thor Eldon",
    "targetId": "7614"
  },
  {
    "source": "Björk",
    "target": "Anna Hinriksdóttir",
    "targetId": "10181"
  },
  {
    "source": "Björk",
    "target": "Arngerður María Árnadóttir",
    "targetId": "10182"
  },
  {
    "source": "Björk",
    "target": "Aðalheiður Þorsteinsdóttir",
    "targetId": "10183"
  },
  {
    "source": "Björk",
    "target": "Guðrún Edda Gunnarsdóttir",
    "targetId": "10184"
  },
  {
    "source": "Björk",
    "target": "Guðrún Finnbjarnardóttir",
    "targetId": "10185"
  },
  {
    "source": "Björk",
    "target": "Jónína Guðrún Kristinsdóttirþ",
    "targetId": "10186"
  },
  {
    "source": "Björk",
    "target": "Benedikt Ingólfsson",
    "targetId": "10187"
  },
  {
    "source": "Björk",
    "target": "Hafsteinn Þórólfsson",
    "targetId": "10188"
  },
  {
    "source": "Björk",
    "target": "Hjálmar Pétursson",
    "targetId": "10189"
  },
  {
    "source": "Björk",
    "target": "Örn Arnarson",
    "targetId": "10190"
  },
  {
    "source": "Björk",
    "target": "Þorvaldur Þorvaldsson",
    "targetId": "10191"
  },
  {
    "source": "Björk",
    "target": "Elfa Ingvadóttir",
    "targetId": "10192"
  },
  {
    "source": "Björk",
    "target": "Hera Björk Þórhallsdóttir",
    "targetId": "10193"
  },
  {
    "source": "Björk",
    "target": "Hugrún Hólmgeirsdóttir",
    "targetId": "10194"
  },
  {
    "source": "Björk",
    "target": "Inga Harðardóttir",
    "targetId": "10195"
  },
  {
    "source": "Björk",
    "target": "Kirstín Erna Blöndal",
    "targetId": "10196"
  },
  {
    "source": "Björk",
    "target": "Björn Thorarensen",
    "targetId": "10197"
  },
  {
    "source": "Björk",
    "target": "Guðmundur Vignir Karlsson",
    "targetId": "10198"
  },
  {
    "source": "Björk",
    "target": "Gísli Magna",
    "targetId": "10199"
  },
  {
    "source": "Björk",
    "target": "Þorbjörn Sigurðsson",
    "targetId": "10200"
  },
  {
    "source": "Björk",
    "target": "Gregory Purnhagen",
    "targetId": "10201"
  },
  {
    "source": "Björk",
    "target": "Mark Bell",
    "targetId": "10202"
  },
  {
    "source": "Björk",
    "target": "Dokaka",
    "targetId": "10203"
  },
  {
    "source": "Björk",
    "target": "Ann De Renais",
    "targetId": "10204"
  },
  {
    "source": "Björk",
    "target": "Emma Brian-Gabbott",
    "targetId": "10205"
  },
  {
    "source": "Björk",
    "target": "Heather Chirncross",
    "targetId": "10206"
  },
  {
    "source": "Björk",
    "target": "Helen Hampton",
    "targetId": "10207"
  },
  {
    "source": "Björk",
    "target": "Helen Pakker",
    "targetId": "10208"
  },
  {
    "source": "Björk",
    "target": "Janet Mooney",
    "targetId": "10209"
  },
  {
    "source": "Björk",
    "target": "Jaqueline Barron",
    "targetId": "10210"
  },
  {
    "source": "Björk",
    "target": "Jenny O'Grady",
    "targetId": "10211"
  },
  {
    "source": "Björk",
    "target": "Judith Sim",
    "targetId": "10212"
  },
  {
    "source": "Björk",
    "target": "Karen Woodhowe",
    "targetId": "10213"
  },
  {
    "source": "Björk",
    "target": "Kim Chandler",
    "targetId": "10214"
  },
  {
    "source": "Björk",
    "target": "Melanie Marshall",
    "targetId": "10215"
  },
  {
    "source": "Björk",
    "target": "Micaela Haslam",
    "targetId": "10216"
  },
  {
    "source": "Björk",
    "target": "Nicki Kennedy",
    "targetId": "10217"
  },
  {
    "source": "Björk",
    "target": "Rachel Chapman",
    "targetId": "10218"
  },
  {
    "source": "Björk",
    "target": "Samantha Shaw",
    "targetId": "10219"
  },
  {
    "source": "Björk",
    "target": "Sarah Eyden",
    "targetId": "10220"
  },
  {
    "source": "Björk",
    "target": "Sarah Simmondi",
    "targetId": "10221"
  },
  {
    "source": "Björk",
    "target": "Tarsha Colt",
    "targetId": "10222"
  },
  {
    "source": "Björk",
    "target": "Yona Dunsford",
    "targetId": "10223"
  },
  {
    "source": "Björk",
    "target": "Nico Muhly",
    "targetId": "10224"
  },
  {
    "source": "Björk",
    "target": "Shlomo",
    "targetId": "10225"
  }
]