{
  "source": "Justin Adams",
  "targets": [
    {
      "name": "Robert Plant",
      "targetId": "296",
      "trackCount": 4
    },
    {
      "name": "Clive Deamer",
      "targetId": "2548",
      "trackCount": 3
    },
    {
      "name": "Charlie Jones",
      "targetId": "3709",
      "trackCount": 3
    },
    {
      "name": "John Baggott",
      "targetId": "3714",
      "trackCount": 3
    },
    {
      "name": "Porl Thompson",
      "targetId": "3715",
      "trackCount": 3
    },
    {
      "name": "May Clee Cadman",
      "targetId": "3716",
      "trackCount": 1
    },
    {
      "name": "Ginny Clee",
      "targetId": "3717",
      "trackCount": 1
    },
    {
      "name": "Skin Tyson",
      "targetId": "3759",
      "trackCount": 1
    },
    {
      "name": "Nicolas Meslien",
      "targetId": "3760",
      "trackCount": 1
    },
    {
      "name": "Mathieu Rousseau",
      "targetId": "3761",
      "trackCount": 1
    }
  ]
}