[
  {
    "source": "Bruce Duff",
    "target": "Don Bolles",
    "targetId": "3264"
  },
  {
    "source": "Bruce Duff",
    "target": "Dinah Cancer",
    "targetId": "4914"
  },
  {
    "source": "Bruce Duff",
    "target": "Paul B. Cutler",
    "targetId": "4915"
  },
  {
    "source": "Bruce Duff",
    "target": "Jussi Lehtisalo",
    "targetId": "4916"
  },
  {
    "source": "Bruce Duff",
    "target": "Tomi Leppänen",
    "targetId": "4917"
  },
  {
    "source": "Bruce Duff",
    "target": "Janne Westerlund",
    "targetId": "4918"
  },
  {
    "source": "Bruce Duff",
    "target": "Make Rättö",
    "targetId": "4919"
  },
  {
    "source": "Bruce Duff",
    "target": "Del Hopkins",
    "targetId": "4956"
  },
  {
    "source": "Bruce Duff",
    "target": "Amy Wichman",
    "targetId": "4957"
  },
  {
    "source": "Bruce Duff",
    "target": "Jeff Dahl",
    "targetId": "4958"
  },
  {
    "source": "Bruce Duff",
    "target": "Rikk Agnew",
    "targetId": "4959"
  }
]