{
  "source": "Paul Kimble",
  "trackCount": 1,
  "tracks": [
    {
      "_id": "174",
      "names": [
        "Ladytron"
      ],
      "releases": [
        {
          "_id": "131",
          "names": [
            "Velvet Goldmine (soundtrack)"
          ]
        }
      ],
      "artists": [
        {
          "_id": "94",
          "names": [
            "The Venus In Furs"
          ]
        }
      ]
    }
  ],
  "targets": [
    {
      "name": "Andrew Mackay",
      "targetId": "492",
      "trackCount": 1,
      "tracks": [
        "174"
      ]
    },
    {
      "name": "Thom Yorke",
      "targetId": "545",
      "trackCount": 1,
      "tracks": [
        "174"
      ]
    },
    {
      "name": "Jonny Greenwood",
      "targetId": "548",
      "trackCount": 1,
      "tracks": [
        "174"
      ]
    },
    {
      "name": "Bernard Butler",
      "targetId": "550",
      "trackCount": 1,
      "tracks": [
        "174"
      ]
    }
  ]
}