{
  "source": "Faye Wong",
  "trackCount": 1,
  "tracks": [
    {
      "_id": "5948",
      "names": [
        "Serpentskirt"
      ],
      "releases": [
        {
          "_id": "1186",
          "names": [
            "Milk And Kisses (Hong Kong edition)"
          ]
        }
      ]
    }
  ],
  "targets": [
    {
      "name": "Elizabeth Fraser",
      "targetId": "614",
      "trackCount": 1,
      "tracks": [
        "5948"
      ]
    },
    {
      "name": "Robin Guthrie",
      "targetId": "615",
      "trackCount": 1,
      "tracks": [
        "5948"
      ]
    },
    {
      "name": "Simon Raymonde",
      "targetId": "619",
      "trackCount": 1,
      "tracks": [
        "5948"
      ]
    }
  ]
}