{
  "source": "Black Thought",
  "targets": [
    {
      "name": "Boots Riley",
      "targetId": "5960"
    },
    {
      "name": "Pam The Funkstress",
      "targetId": "5961"
    },
    {
      "name": "Talib Kweli",
      "targetId": "5963"
    },
    {
      "name": "Ron Gadson",
      "targetId": "5967"
    },
    {
      "name": "Michael Aaberg",
      "targetId": "5968"
    },
    {
      "name": "James Henry",
      "targetId": "5969"
    },
    {
      "name": "Eric McFadden",
      "targetId": "5970"
    },
    {
      "name": "Dave Council",
      "targetId": "5971"
    },
    {
      "name": "Viveca Hawkings",
      "targetId": "5972"
    }
  ]
}