[
  {
    "source": "Susanna Hoffs",
    "target": "Simon Le Bon"
  },
  {
    "source": "Susanna Hoffs",
    "target": "Warren Cuccurullo"
  },
  {
    "source": "Susanna Hoffs",
    "target": "Steve Ferrone"
  },
  {
    "source": "Susanna Hoffs",
    "target": "Matthew Sweet"
  },
  {
    "source": "Susanna Hoffs",
    "target": "Kendra Smith"
  },
  {
    "source": "Susanna Hoffs",
    "target": "Rob Burger"
  },
  {
    "source": "Susanna Hoffs",
    "target": "Jonathan Elias"
  },
  {
    "source": "Susanna Hoffs",
    "target": "Sherman Foote"
  },
  {
    "source": "Susanna Hoffs",
    "target": "Alex Lasarenko"
  },
  {
    "source": "Susanna Hoffs",
    "target": "Daniel C. Hill"
  },
  {
    "source": "Susanna Hoffs",
    "target": "Allan Schwartzberg"
  },
  {
    "source": "Susanna Hoffs",
    "target": "David Roback"
  },
  {
    "source": "Susanna Hoffs",
    "target": "Will Glenn"
  },
  {
    "source": "Susanna Hoffs",
    "target": "Michael Quercio"
  },
  {
    "source": "Susanna Hoffs",
    "target": "Vicki Peterson"
  },
  {
    "source": "Susanna Hoffs",
    "target": "Lucinda Williams"
  },
  {
    "source": "Susanna Hoffs",
    "target": "Butch Norton"
  },
  {
    "source": "Susanna Hoffs",
    "target": "David Sutton"
  },
  {
    "source": "Susanna Hoffs",
    "target": "Chet Lyster"
  },
  {
    "source": "Susanna Hoffs",
    "target": "Doug Pettibone"
  }
]