{
  "source": "Chris August",
  "trackCount": 1,
  "tracks": [
    {
      "_id": "8819",
      "names": [
        "A Public Affair"
      ],
      "releases": [
        {
          "_id": "1690",
          "names": [
            "A Public Affair"
          ]
        }
      ]
    }
  ],
  "targets": [
    {
      "name": "Siedah Garrett",
      "targetId": "2081",
      "trackCount": 1,
      "tracks": [
        "8819"
      ]
    },
    {
      "name": "Jessica Simpson",
      "targetId": "5306",
      "trackCount": 1,
      "tracks": [
        "8819"
      ]
    },
    {
      "name": "Dorian Holly",
      "targetId": "8194",
      "trackCount": 1,
      "tracks": [
        "8819"
      ]
    },
    {
      "name": "Niki Harris",
      "targetId": "8195",
      "trackCount": 1,
      "tracks": [
        "8819"
      ]
    },
    {
      "name": "Sherree Brown",
      "targetId": "8196",
      "trackCount": 1,
      "tracks": [
        "8819"
      ]
    }
  ]
}