{
  "source": "Bobby Previte",
  "trackCount": 2,
  "tracks": [
    {
      "_id": "8852",
      "names": [
        "Clap Hands"
      ],
      "releases": [
        {
          "_id": "1698",
          "names": [
            "Rain Dogs"
          ]
        }
      ],
      "artists": [
        {
          "_id": "376",
          "names": [
            "Tom Waits"
          ]
        }
      ]
    },
    {
      "_id": "9140",
      "names": [
        "Open Letter To Duke"
      ],
      "releases": [
        {
          "_id": "1750",
          "names": [
            "Weird Nightmare: Meditations On Mingus"
          ]
        }
      ],
      "artists": [
        {
          "_id": "1349",
          "names": [
            "Bobby Previte"
          ]
        }
      ]
    }
  ],
  "targets": [
    {
      "name": "Michael Blair",
      "targetId": "662",
      "trackCount": 1,
      "tracks": [
        "8852"
      ]
    },
    {
      "name": "Tom Waits",
      "targetId": "1713",
      "trackCount": 1,
      "tracks": [
        "8852"
      ]
    },
    {
      "name": "Marc Ribot",
      "targetId": "3588",
      "trackCount": 1,
      "tracks": [
        "8852"
      ]
    },
    {
      "name": "Tony Trischka",
      "targetId": "4839",
      "trackCount": 1,
      "tracks": [
        "9140"
      ]
    },
    {
      "name": "Tony Garnier",
      "targetId": "5456",
      "trackCount": 1,
      "tracks": [
        "8852"
      ]
    },
    {
      "name": "Stephen Taylor Arvizu Hodges",
      "targetId": "8222",
      "trackCount": 1,
      "tracks": [
        "8852"
      ]
    },
    {
      "name": "Howard Levy",
      "targetId": "8436",
      "trackCount": 1,
      "tracks": [
        "9140"
      ]
    },
    {
      "name": "Barry Mitterhoff",
      "targetId": "8437",
      "trackCount": 1,
      "tracks": [
        "9140"
      ]
    },
    {
      "name": "Susan Evans",
      "targetId": "8438",
      "trackCount": 1,
      "tracks": [
        "9140"
      ]
    },
    {
      "name": "Bob Stewart",
      "targetId": "8439",
      "trackCount": 1,
      "tracks": [
        "9140"
      ]
    },
    {
      "name": "Kenny Kosek",
      "targetId": "8440",
      "trackCount": 1,
      "tracks": [
        "9140"
      ]
    }
  ]
}