[
  {
    "source": "Walt Harrah",
    "target": "Bob Dylan",
    "targetId": "35"
  },
  {
    "source": "Walt Harrah",
    "target": "David Hidalgo",
    "targetId": "285"
  },
  {
    "source": "Walt Harrah",
    "target": "Patrick Warren",
    "targetId": "3870"
  },
  {
    "source": "Walt Harrah",
    "target": "Tony Garnier",
    "targetId": "5456"
  },
  {
    "source": "Walt Harrah",
    "target": "Phil Upchurch",
    "targetId": "8266"
  },
  {
    "source": "Walt Harrah",
    "target": "Donnie Herron",
    "targetId": "8267"
  },
  {
    "source": "Walt Harrah",
    "target": "George Recile",
    "targetId": "8268"
  },
  {
    "source": "Walt Harrah",
    "target": "Amanda Barrett",
    "targetId": "8269"
  },
  {
    "source": "Walt Harrah",
    "target": "Bill Cantos",
    "targetId": "8270"
  },
  {
    "source": "Walt Harrah",
    "target": "Randy Crenshaw",
    "targetId": "8271"
  },
  {
    "source": "Walt Harrah",
    "target": "Abby DeWald",
    "targetId": "8272"
  },
  {
    "source": "Walt Harrah",
    "target": "Nicole Eva Emery",
    "targetId": "8273"
  },
  {
    "source": "Walt Harrah",
    "target": "Robert Joyce",
    "targetId": "8275"
  }
]