[
  {
    "source": "Snowy White",
    "target": "Cyndi Lauper",
    "targetId": "64"
  },
  {
    "source": "Snowy White",
    "target": "Thomas Dolby",
    "targetId": "859"
  },
  {
    "source": "Snowy White",
    "target": "Roger Waters",
    "targetId": "2003"
  },
  {
    "source": "Snowy White",
    "target": "Rick DiFonzo",
    "targetId": "3442"
  },
  {
    "source": "Snowy White",
    "target": "Peter Wood",
    "targetId": "7845"
  },
  {
    "source": "Snowy White",
    "target": "Graham Broad",
    "targetId": "8414"
  },
  {
    "source": "Snowy White",
    "target": "Nick Glennie-Smith",
    "targetId": "8415"
  }
]